{
  "applications": "*",
  "changelogDate": "20220613081246",
  "dto": "no",
  "embedded": false,
  "entityTableName": "category",
  "fields": [
    {
      "fieldName": "title",
      "fieldType": "String"
    },
    {
      "fieldName": "parentcategory",
      "fieldType": "Long"
    },
    {
      "fieldName": "attributes",
      "fieldType": "String"
    },
    {
      "fieldName": "level",
      "fieldType": "String"
    },
    {
      "fieldName": "description",
      "fieldType": "String"
    },
    {
      "fieldName": "categoryStatus",
      "fieldType": "Boolean"
    }
  ],
  "fluentMethods": true,
  "jpaMetamodelFiltering": false,
  "name": "Category",
  "pagination": "no",
  "readOnly": false,
  "relationships": [
    {
      "otherEntityName": "category",
      "otherEntityRelationshipName": "category",
      "ownerSide": true,
      "relationshipName": "category",
      "relationshipType": "one-to-one"
    },
    {
      "otherEntityName": "product",
      "otherEntityRelationshipName": "category",
      "relationshipName": "category",
      "relationshipType": "one-to-many"
    }
  ],
  "service": "no"
}
